LICENSE
MANIFEST.in
README.md
setup.py
ISAT/ISAT_new_64.svg
ISAT/__init__.py
ISAT/annotation.py
ISAT/configs.py
ISAT/icons.qrc
ISAT/icons_rc.py
ISAT/isat.yaml
ISAT/main.py
ISAT/software.yaml
ISAT/formats/__init__.py
ISAT/formats/coco.py
ISAT/formats/isat.py
ISAT/formats/labelme.py
ISAT/formats/voc.py
ISAT/formats/voc_detection.py
ISAT/formats/yolo.py
ISAT/segment_any/__init__.py
ISAT/segment_any/gpu_resource.py
ISAT/segment_any/model_zoo.py
ISAT/segment_any/segment_any.py
ISAT/segment_any/edge_sam/__init__.py
ISAT/segment_any/edge_sam/automatic_mask_generator.py
ISAT/segment_any/edge_sam/build_sam.py
ISAT/segment_any/edge_sam/predictor.py
ISAT/segment_any/edge_sam/modeling/__init__.py
ISAT/segment_any/edge_sam/modeling/common.py
ISAT/segment_any/edge_sam/modeling/image_encoder.py
ISAT/segment_any/edge_sam/modeling/mask_decoder.py
ISAT/segment_any/edge_sam/modeling/prompt_encoder.py
ISAT/segment_any/edge_sam/modeling/rep_vit.py
ISAT/segment_any/edge_sam/modeling/sam.py
ISAT/segment_any/edge_sam/modeling/transformer.py
ISAT/segment_any/edge_sam/onnx/__init__.py
ISAT/segment_any/edge_sam/onnx/predictor_onnx.py
ISAT/segment_any/edge_sam/utils/__init__.py
ISAT/segment_any/edge_sam/utils/amg.py
ISAT/segment_any/edge_sam/utils/coreml.py
ISAT/segment_any/edge_sam/utils/transforms.py
ISAT/segment_any/mobile_sam/__init__.py
ISAT/segment_any/mobile_sam/automatic_mask_generator.py
ISAT/segment_any/mobile_sam/build_sam.py
ISAT/segment_any/mobile_sam/predictor.py
ISAT/segment_any/mobile_sam/modeling/__init__.py
ISAT/segment_any/mobile_sam/modeling/common.py
ISAT/segment_any/mobile_sam/modeling/image_encoder.py
ISAT/segment_any/mobile_sam/modeling/mask_decoder.py
ISAT/segment_any/mobile_sam/modeling/prompt_encoder.py
ISAT/segment_any/mobile_sam/modeling/sam.py
ISAT/segment_any/mobile_sam/modeling/tiny_vit_sam.py
ISAT/segment_any/mobile_sam/modeling/transformer.py
ISAT/segment_any/mobile_sam/utils/__init__.py
ISAT/segment_any/mobile_sam/utils/amg.py
isat_sam.egg-info/PKG-INFO
isat_sam.egg-info/SOURCES.txt
isat_sam.egg-info/dependency_links.txt
isat_sam.egg-info/entry_points.txt
isat_sam.egg-info/requires.txt
isat_sam.egg-info/top_level.txt