Metadata-Version: 2.4
Name: isat-sam
Version: 1.5.2
Summary: Interactive semi-automatic annotation tool for image segmentation based on SAM(segment anything model).
Home-page: https://github.com/yatengLG/ISAT_with_segment_anything
Author: yatengLG
Author-email: yatenglg@foxmail.com
License: Apache2.0
Keywords: annotation tool,segment anything,image annotation,semantic segmentation,instance segmentation
Classifier: Intended Audience :: Developers
Classifier: Intended Audience :: Science/Research
Classifier: Development Status :: 5 - Production/Stable
Classifier: Natural Language :: Chinese (Simplified)
Classifier: Natural Language :: English
Classifier: License :: OSI Approved :: Apache Software License
Classifier: Operating System :: OS Independent
Classifier: Programming Language :: Python
Classifier: Programming Language :: Python :: 3.8
Classifier: Programming Language :: Python :: 3.9
Classifier: Programming Language :: Python :: 3.10
Requires-Python: >=3.8
License-File: LICENSE
Requires-Dist: imgviz
Requires-Dist: scikit-image
Requires-Dist: numpy
Requires-Dist: opencv_python_headless
Requires-Dist: pillow
Requires-Dist: pyqt5
Requires-Dist: pyyaml
Requires-Dist: torch>=2.1.1
Requires-Dist: torchvision
Requires-Dist: pycocotools
Requires-Dist: timm
Requires-Dist: shapely
Requires-Dist: hydra-core>=1.3.2
Requires-Dist: tqdm>=4.66.1
Requires-Dist: fuzzywuzzy
Requires-Dist: python-Levenshtein
Requires-Dist: iopath
Requires-Dist: orjson
Requires-Dist: pydicom
Requires-Dist: requests
Requires-Dist: einops
Requires-Dist: psutil
Requires-Dist: ftfy
Requires-Dist: regex
Dynamic: author
Dynamic: author-email
Dynamic: classifier
Dynamic: description
Dynamic: description-content-type
Dynamic: home-page
Dynamic: keywords
Dynamic: license
Dynamic: license-file
Dynamic: requires-dist
Dynamic: requires-python
Dynamic: summary
